monkeytools/__init__.py
monkeytools/array_methods.py
monkeytools/sorting.py
monkeytools/utils.py
monkeytools-0.4.dist-info/LICENSE
monkeytools-0.4.dist-info/METADATA
monkeytools-0.4.dist-info/WHEEL
monkeytools-0.4.dist-info/top_level.txt
monkeytools-0.4.dist-info/RECORD
