Metadata-Version: 2.1
Name: monkeytools
Version: 0.4
Summary: A personal collection of algorithms and tools for the standard code monkey.
Home-page: https://github.com/mr-devs/monkeytools
Author: Matthew DeVerna
Author-email: mdeverna@iu.edu
License: MIT
Download-URL: https://github.com/mr-devs/monkeytools
Project-URL: Documentation, https://github.com/mr-devs/monkeytools
Project-URL: Issue Tracker, https://github.com/mr-devs/monkeytools/issues
Project-URL: Source Code, https://github.com/mr-devs/monkeytools
Platform: UNKNOWN
Requires-Python: >=3.5
License-File: LICENSE
